legalvector_mcp/__init__.py
legalvector_mcp/server.py
legalvector_mcp-1.0.2.dist-info/licenses/LICENSE
legalvector_mcp-1.0.2.dist-info/METADATA
legalvector_mcp-1.0.2.dist-info/WHEEL
legalvector_mcp-1.0.2.dist-info/entry_points.txt
legalvector_mcp-1.0.2.dist-info/top_level.txt
legalvector_mcp-1.0.2.dist-info/RECORD
