Metadata-Version: 2.4
Name: legalvector-mcp
Version: 1.0.2
Summary: Legal technology intelligence MCP server for Claude Desktop
Home-page: https://github.com/docketlabs/LegalVector
Author: DocketLabs
Author-email: DocketLabs <contact@docketlabs.com>
License: MIT
Project-URL: Homepage, https://github.com/docketlabs/LegalVector
Project-URL: Documentation, https://github.com/docketlabs/LegalVector/blob/main/README.md
Project-URL: Repository, https://github.com/docketlabs/LegalVector
Project-URL: Bug Reports, https://github.com/docketlabs/LegalVector/issues
Keywords: legal-tech,ai,law-firms,mcp-server,claude-desktop
Classifier: Development Status :: 5 - Production/Stable
Classifier: Intended Audience :: Developers
Classifier: Topic :: Software Development :: Libraries :: Python Modules
Classifier: License :: OSI Approved :: MIT License
Classifier: Programming Language :: Python :: 3
Classifier: Programming Language :: Python :: 3.8
Classifier: Programming Language :: Python :: 3.9
Classifier: Programming Language :: Python :: 3.10
Classifier: Programming Language :: Python :: 3.11
Requires-Python: >=3.8
License-File: LICENSE
Requires-Dist: supabase>=2.0.0
Requires-Dist: pinecone>=5.0.0
Requires-Dist: openai>=1.0.0
Requires-Dist: typing-extensions>=4.0.0
Dynamic: author
Dynamic: home-page
Dynamic: license-file
Dynamic: requires-python
